{"namedChunkGroups":{"polyfill":{"name":"polyfill","assets":[{"name":"webpack-runtime-6614fa3a01b0afa51938.js","size":4284},{"name":"polyfill-7ce5d8d248ca4702b661.js","size":82608}],"filteredAssets":0,"assetsSize":86892,"filteredAuxiliaryAssets":2,"auxiliaryAssetsSize":219333},"app":{"name":"app","assets":[{"name":"webpack-runtime-6614fa3a01b0afa51938.js","size":4284},{"name":"styles.02cddbe42bf11a80448d.css","size":4704},{"name":"framework-ed9db9aefe57b36b5b4e.js","size":127842},{"name":"app-e58896397d61cd7fefb3.js","size":55577}],"filteredAssets":0,"assetsSize":192407,"filteredAuxiliaryAssets":3,"auxiliaryAssetsSize":567387},"component---src-page-template-home-tsx":{"name":"component---src-page-template-home-tsx","assets":[{"name":"styles.02cddbe42bf11a80448d.css","size":4704},{"name":"commons-a2a98c1edea90d4d2068.js","size":15755},{"name":"component---src-page-template-home-tsx-f7cbb09315948e62f292.js","size":1636}],"filteredAssets":0,"assetsSize":22095,"filteredAuxiliaryAssets":2,"auxiliaryAssetsSize":70508},"component---src-page-template-post-tsx":{"name":"component---src-page-template-post-tsx","assets":[{"name":"styles.02cddbe42bf11a80448d.css","size":4704},{"name":"commons-a2a98c1edea90d4d2068.js","size":15755},{"name":"component---src-page-template-post-tsx-592e6be82d55b05cd91c.js","size":1119}],"filteredAssets":0,"assetsSize":21578,"filteredAuxiliaryAssets":2,"auxiliaryAssetsSize":68764}},"assetsByChunkName":{"polyfill":["webpack-runtime-6614fa3a01b0afa51938.js","polyfill-7ce5d8d248ca4702b661.js"],"app":["webpack-runtime-6614fa3a01b0afa51938.js","styles.02cddbe42bf11a80448d.css","framework-ed9db9aefe57b36b5b4e.js","app-e58896397d61cd7fefb3.js"],"component---src-page-template-home-tsx":["styles.02cddbe42bf11a80448d.css","commons-a2a98c1edea90d4d2068.js","component---src-page-template-home-tsx-f7cbb09315948e62f292.js"],"component---src-page-template-post-tsx":["styles.02cddbe42bf11a80448d.css","commons-a2a98c1edea90d4d2068.js","component---src-page-template-post-tsx-592e6be82d55b05cd91c.js"]},"childAssetsByChunkName":{}}